langchain_wiproai/__init__.py
langchain_wiproai/chat_models.py
langchain_wiproai-0.1.0.dist-info/licenses/LICENSE
langchain_wiproai-0.1.0.dist-info/METADATA
langchain_wiproai-0.1.0.dist-info/WHEEL
langchain_wiproai-0.1.0.dist-info/top_level.txt
langchain_wiproai-0.1.0.dist-info/RECORD
