Metadata-Version: 2.4
Name: langchain-wiproai
Version: 0.1.0
Summary: Wipro AI integration for LangChain
Home-page: https://github.com/Wipro-AI/langchain-wiproai
Author: Wipro AI Team
Author-email: Your Name <your.email@example.com>
License: MIT
Project-URL: Homepage, https://github.com/yourusername/langchain-wiproai
Project-URL: Repository, https://github.com/yourusername/langchain-wiproai
Project-URL: Documentation, https://github.com/yourusername/langchain-wiproai#readme
Keywords: langchain,wiproai,llm,ai
Classifier: Development Status :: 4 - Beta
Classifier: Intended Audience :: Developers
Classifier: License :: OSI Approved :: MIT License
Classifier: Programming Language :: Python :: 3
Requires-Python: >=3.8
License-File: LICENSE
Requires-Dist: langchain-core<0.4.0,>=0.3.0
Requires-Dist: requests>=2.25.0
Requires-Dist: pydantic<3.0.0,>=2.0.0
Provides-Extra: dev
Requires-Dist: pytest>=7.0.0; extra == "dev"
Requires-Dist: black>=23.0.0; extra == "dev"
Requires-Dist: mypy>=1.0.0; extra == "dev"
Requires-Dist: ruff>=0.1.0; extra == "dev"
Dynamic: author
Dynamic: home-page
Dynamic: license-file
Dynamic: requires-python
